Workbook

Sheet Inputs
A1: KKBox auto-renew nudge pilot: business case
A2: Blue text = input you can change. Yellow fill = assumption, not data. All other numbers are formulas.
A4: Input | B4: Value | C4: Source
A5: Manual-renew customers in sample | B5: 1015 | C5: dashboard_outputs/renewal_summary.csv
A6: Baseline churn, manual-renew | B6: 0.4158 | C6: dashboard_outputs/renewal_summary.csv
A7: Avg monthly revenue of a churned manual-renew customer (NTD) | B7: 140.76 | C7: dashboard_outputs/scenario_summary.csv
A9: Scenario levers are on the Scenarios sheet (row 5 to 10).

Sheet Scenarios
A1: Costed scenarios (sample scale: customers contacted = manual-renew sample)
A2: Levers in yellow are assumptions. Change them to test the case.
A4: Lever (assumption) | B4: Low | C4: Base | D4: High
A5: Churn reduction (percentage points) | B5: 0.02 | C5: 0.05 | D5: 0.1
A6: Months a saved customer stays | B6: 3 | C6: 6 | D6: 12
A7: Contribution margin on revenue | B7: 0.25 | C7: 0.3 | D7: 0.35
A8: Contact cost per customer (NTD) | B8: 5 | C8: 2 | D8: 1
A9: Opt-in rate to auto-renew | B9: 0.2 | C9: 0.3 | D9: 0.4
A10: Incentive per opt-in (NTD) | B10: 30 | C10: 0 | D10: 0
A12: Result (formula) | B12: Low | C12: Base | D12: High
A13: Customers contacted | B13: =Inputs!$B$5 | C13: =Inputs!$B$5 | D13: =Inputs!$B$5
A14: Avoided churners | B14: =B13*B5 | C14: =C13*C5 | D14: =D13*D5
A15: Retained contribution (NTD) | B15: =B14*Inputs!$B$7*B7*B6 | C15: =C14*Inputs!$B$7*C7*C6 | D15: =D14*Inputs!$B$7*D7*D6
A16: Programme cost (NTD) | B16: =B13*B8+B13*B9*B10 | C16: =C13*C8+C13*C9*C10 | D16: =D13*D8+D13*D9*D10
A17: Net value (NTD) | B17: =B15-B16 | C17: =C15-C16 | D17: =D15-D16
A18: Return on cost | B18: =IFERROR(B17/B16,"n/a") | C18: =IFERROR(C17/C16,"n/a") | D18: =IFERROR(D17/D16,"n/a")
A19: Break-even churn reduction (points) | B19: =IFERROR(B16/(B13*Inputs!$B$7*B7*B6),0) | C19: =IFERROR(C16/(C13*Inputs!$B$7*C7*C6),0) | D19: =IFERROR(D16/(D13*Inputs!$B$7*D7*D6),0)
A20: Assumed effect vs break-even | B20: =IF(B5>=B19,"Above break-even","Below break-even") | C20: =IF(C5>=C19,"Above break-even","Below break-even") | D20: =IF(D5>=D19,"Above break-even","Below break-even")
A22: Sensitivity: net value (NTD) by churn reduction, other levers at Base
A23: Churn reduction (points) | B23: Net value (NTD)
A24: 0.01 | B24: =$C$13*A24*Inputs!$B$7*$C$7*$C$6-$C$16
A25: 0.02 | B25: =$C$13*A25*Inputs!$B$7*$C$7*$C$6-$C$16
A26: 0.03 | B26: =$C$13*A26*Inputs!$B$7*$C$7*$C$6-$C$16
A27: 0.05 | B27: =$C$13*A27*Inputs!$B$7*$C$7*$C$6-$C$16
A28: 0.07 | B28: =$C$13*A28*Inputs!$B$7*$C$7*$C$6-$C$16
A29: 0.1 | B29: =$C$13*A29*Inputs!$B$7*$C$7*$C$6-$C$16
A31: Sample scale only. At full scale, multiply customers contacted by the eligible volume. Figures are what-ifs, not forecasts.

Sheet Pilot
A1: Pilot sample size (two-proportion test, 1:1 randomisation)
A3: Input | B3: Value
A4: Baseline churn (from Inputs) | B4: =Inputs!B6
A5: Minimum effect to detect (points) | B5: 0.05
A6: Significance (two-sided) | B6: 0.05
A7: Power | B7: 0.8
A9: Result (formula) | B9: Value
A10: Customers per arm | B10: =ROUNDUP((NORMSINV(1-B6/2)+NORMSINV(B7))^2*(B4*(1-B4)+(B4-B5)*(1-(B4-B5)))/B5^2,0)
A11: Total eligible customers needed | B11: =2*B10
A13: Monthly eligible volume at full scale
A14: Months of enrolment needed | B14: =IF(B13="","Enter volume in B13",ROUNDUP(B11/B13,0))
A16: The 7,500-customer analysis sample is not the pilot population. The pilot runs on the full customer base, so feasibility depends on B13.

Sheet Assumption log
A1: Item | B1: Type | C1: Where | D1: Why it matters
A2: Churn reduction 2 / 5 / 10 points | B2: Assumption | C2: Scenarios row 5 | D2: Drives all value
A3: Months retained 3 / 6 / 12 | B3: Assumption | C3: Scenarios row 6 | D3: Scales value linearly
A4: Margin 25% / 30% / 35% | B4: Assumption | C4: Scenarios row 7 | D4: Revenue is not profit
A5: Contact cost 5 / 2 / 1 NTD | B5: Assumption | C5: Scenarios row 8 | D5: Main programme cost
A6: Opt-in rate, incentive | B6: Assumption | C6: Scenarios rows 9-10 | D6: Only matters with an incentive
A7: 5-point minimum effect | B7: Assumption | C7: Pilot B5 | D7: Smaller effect needs a bigger pilot
A8: Monthly eligible volume | B8: Unknown | C8: Pilot B13 | D8: Decides pilot duration
A9: Customers, churn, revenue | B9: Data (sample) | C9: Inputs B5:B7 | D9: 2017 sample, not company-wide
